lamr/__init__.py
lamr/code/cal.py
lamr/code/cal.yml
lamr/code/logo.py
lamr/code/logo.yml
lamr/code/requirements.txt
lamr/code/text.py
lamr/code/x.py
lamr/file_handlers.py
lamr/show.py
lamr/topics/.vitepress/config.mjs
lamr/topics/_values.md
lamr/topics/_variables.md
lamr/topics/api-examples.md
lamr/topics/constants.md
lamr/topics/data_science_projects.md
lamr/topics/index.md
lamr/topics/markdown-examples.md
lamr/topics/programming.md
lamr/topics/README.md
lamr/topics/variable_assignment.md
lamr/topics/variable_naming.md
lamr/topics/x.md
lamr/yaml_model.py
lamr-0.2.2.dist-info/entry_points.txt
lamr-0.2.2.dist-info/METADATA
lamr-0.2.2.dist-info/WHEEL
lamr-0.2.2.dist-info/RECORD
