Metadata-Version: 2.1
Name: lamr
Version: 0.2.2
Summary: Python course for beginners fully free at your own command line.
Home-page: https://github.com/epogrebnyak/bootcamp
License: GNU
Author: Evgeny Pogrebnyak
Author-email: e.pogrebnyak@gmail.com
Requires-Python: >=3.10,<4.0
Classifier: License :: Other/Proprietary License
Classifier: Programming Language :: Python :: 3
Classifier: Programming Language :: Python :: 3.10
Classifier: Programming Language :: Python :: 3.11
Classifier: Programming Language :: Python :: 3.12
Requires-Dist: ghp-import (>=2.1.0,<3.0.0)
Requires-Dist: pydantic (>=2.6.0,<3.0.0)
Requires-Dist: pygments (>=2.17.2,<3.0.0)
Requires-Dist: python-frontmatter (>=1.1.0,<2.0.0)
Requires-Dist: pyyaml (>=6.0.1,<7.0.0)
Requires-Dist: rich (>=13.7.0,<14.0.0)
Requires-Dist: typer (>=0.9.0,<0.10.0)
Requires-Dist: types-pygments (>=2.17.0.20240106,<3.0.0.0)
Requires-Dist: types-pyyaml (>=6.0.12.12,<7.0.0.0)
Project-URL: Repository, https://github.com/epogrebnyak/bootcamp
